askcli
tests
