Metadata-Version: 1.1
Name: askcli
Version: 1.0.3
Summary: Generate interactive menus in a python script. Like yes/no question and menu action.
Home-page: https://github.com/thivolle-cazat-cedric/py-askcli/tree/1.0.0/askcli
Author: THIVOLLE-CAZAT cedric
Author-email: UNKNOWN
License: BSD
Keywords: scipting menu yes/no question
Platform: UNKNOWN
Classifier: Topic :: Utilities
Classifier: License :: OSI Approved :: BSD License
